[{"Year":2000,"Value":2.1738},{"Year":2001,"Value":1.9051},{"Year":2002,"Value":1.64116},{"Year":2003,"Value":1.60996},{"Year":2004,"Value":1.66942},{"Year":2005,"Value":1.74613},{"Year":2006,"Value":1.79491},{"Year":2007,"Value":1.59747},{"Year":2008,"Value":1.87925},{"Year":2009,"Value":2.57787},{"Year":2010,"Value":3.18811},{"Year":2011,"Value":3.70904},{"Year":2012,"Value":4.3967},{"Year":2013,"Value":4.60397},{"Year":2014,"Value":4.70311},{"Year":2015,"Value":4.79771},{"Year":2016,"Value":4.9131},{"Year":2017,"Value":5.20921},{"Year":2018,"Value":4.83018},{"Year":2019,"Value":4.45059}]